{
  "goid": "24e6fd7c5b6fb3a96690246c8ac492ec",
  "guid": "a4448be1-9b0e-417f-b498-8a268cadf8a5",
  "name": "#OTK OVP Configuration",
  "policyType": "FRAGMENT",
  "checksum": "b87698cb946fa80914bc1a8aa1b1bb7c6d4cbf88",
  "folderPath": "/OTK/Customizations",
  "soap": false,
  "policy": {
    "xml": "<wsp:Policy xmlns:L7p=\"http://www.layer7tech.com/ws/policy\" xmlns:wsp=\"http://schemas.xmlsoap.org/ws/2002/12/policy\">\n    <wsp:All wsp:Usage=\"Required\">\n        <L7p:CommentAssertion>\n            <L7p:Comment stringValue=\"Target Configuration Policy: &quot;OTK OVP Configuration&quot;\"/>\n        </L7p:CommentAssertion>\n        <L7p:CommentAssertion>\n            <L7p:Comment stringValue=\"=== Set custom values for Context Variables below ===\"/>\n        </L7p:CommentAssertion>\n        <L7p:CommentAssertion>\n            <L7p:Comment stringValue=\"=== Add any new Context Variables or extensions below ===\"/>\n        </L7p:CommentAssertion>\n    </wsp:All>\n</wsp:Policy>"
  }
}