{
  "goid": "dbb8f21825ca7b9e957d6f1c7d7ff1e5",
  "guid": "2a24ce58-fabf-4b80-a09a-0958dcd67fe0",
  "name": "OTK openid response_modes_supported",
  "checksum": "789b1563b0d472f807e44309d327efa2c7429421",
  "policyName": "OTK openid response_modes_supported",
  "encassArgs": [
    {
      "name": "custom",
      "type": "STRING",
      "ordinal": 1,
      "guiPrompt": true,
      "guiLabel": "Custom"
    }
  ],
  "encassResults": [
    {
      "name": "custom_data",
      "type": "STRING"
    },
    {
      "name": "discovery.endpoint.enabled",
      "type": "STRING"
    },
    {
      "name": "response_modes_supported",
      "type": "STRING"
    }
  ],
  "properties": [
    {
      "name": "allowTracing",
      "value": "false"
    },
    {
      "name": "paletteFolder",
      "value": "customAssertions"
    },
    {
      "name": "paletteIconResourceName",
      "value": "oauth.png"
    },
    {
      "name": "passMetricsToParent",
      "value": "false"
    }
  ]
}